Topsis_102017182_sandhya_goyal/__init__.py
Topsis_102017182_sandhya_goyal/topsis.py
Topsis_102017182_sandhya_goyal-1.0.0.dist-info/LICENSE
Topsis_102017182_sandhya_goyal-1.0.0.dist-info/METADATA
Topsis_102017182_sandhya_goyal-1.0.0.dist-info/WHEEL
Topsis_102017182_sandhya_goyal-1.0.0.dist-info/top_level.txt
Topsis_102017182_sandhya_goyal-1.0.0.dist-info/RECORD
