Metadata-Version: 2.1
Name: Topsis-102017182-sandhya-goyal
Version: 1.0.0
Summary: This package performs the topsis(multiple criterion decision making) on a pandas dataframe and return the rank and topsis score.
Home-page: https://github.com/sandhya-goyal/Topsis_102017182.git
Author: Sandhya Goyal
Author-email: sandhyagoyal2002@gmail.com
License: MIT
Download-URL: https://github.com/sandhya-goyal/Topsis_102017182/archive/refs/tags/v1.0.0.tar.gz
Keywords: TOPSIS,MCDM,DECISION,MAKING
Platform: UNKNOWN
Classifier: Development Status :: 3 - Alpha
Classifier: Intended Audience :: Developers
Classifier: Topic :: Software Development :: Build Tools
Classifier: License :: OSI Approved :: MIT License
Classifier: Programming Language :: Python :: 3
Classifier: Programming Language :: Python :: 3.4
Classifier: Programming Language :: Python :: 3.5
Classifier: Programming Language :: Python :: 3.6
License-File: LICENSE
Requires-Dist: numpy
Requires-Dist: pandas
